[
  {
    "line": 2,
    "elements": [
      {
        "start_timestamp": "2023-12-16T02:57:17.668Z",
        "before": [
          {
            "result": {
              "duration": 3149111500,
              "status": "passed"
            },
            "match": {
              "location": "hooks.FrameworkHook.setUpConfigFile(io.cucumber.java.Scenario)"
            }
          }
        ],
        "line": 12,
        "name": "Data Driven Testing in scenario outline",
        "description": "",
        "id": "data-driven-testing;data-driven-testing-in-scenario-outline;;2",
        "after": [
          {
            "result": {
              "duration": 183439300,
              "status": "passed"
            },
            "match": {
              "location": "hooks.FrameworkHook.dismantleDriver(io.cucumber.java.Scenario)"
            }
          }
        ],
        "type": "scenario",
        "keyword": "Scenario Outline",
        "steps": [
          {
            "result": {
              "duration": 3002000,
              "status": "passed"
            },
            "line": 6,
            "name": "Name of employee \"Bharti\"",
            "match": {
              "arguments": [
                {
                  "val": "\"Bharti\"",
                  "offset": 17
                }
              ],
              "location": "stepdefinition.DataDrivenTesting.name_of_employee(java.lang.String)"
            },
            "keyword": "Given "
          },
          {
            "result": {
              "duration": 503000,
              "status": "passed"
            },
            "line": 7,
            "name": "salary of employee \"90000\" in step",
            "match": {
              "arguments": [
                {
                  "val": "\"90000\"",
                  "offset": 19
                }
              ],
              "location": "stepdefinition.DataDrivenTesting.salary_of_employee_in_step(java.lang.String)"
            },
            "keyword": "When "
          },
          {
            "result": {
              "duration": 1630900,
              "status": "passed"
            },
            "line": 8,
            "name": "company of employee \"IBM\" in step",
            "match": {
              "arguments": [
                {
                  "val": "\"IBM\"",
                  "offset": 20
                }
              ],
              "location": "stepdefinition.DataDrivenTesting.company_of_employee_in_step(java.lang.String)"
            },
            "keyword": "Then "
          }
        ],
        "tags": [
          {
            "name": "@ddt"
          }
        ]
      },
      {
        "start_timestamp": "2023-12-16T02:57:21.100Z",
        "before": [
          {
            "result": {
              "duration": 2068323300,
              "status": "passed"
            },
            "match": {
              "location": "hooks.FrameworkHook.setUpConfigFile(io.cucumber.java.Scenario)"
            }
          }
        ],
        "line": 13,
        "name": "Data Driven Testing in scenario outline",
        "description": "",
        "id": "data-driven-testing;data-driven-testing-in-scenario-outline;;3",
        "after": [
          {
            "result": {
              "duration": 125660400,
              "status": "passed"
            },
            "match": {
              "location": "hooks.FrameworkHook.dismantleDriver(io.cucumber.java.Scenario)"
            }
          }
        ],
        "type": "scenario",
        "keyword": "Scenario Outline",
        "steps": [
          {
            "result": {
              "status": "passed"
            },
            "line": 6,
            "name": "Name of employee \"Anjali\"",
            "match": {
              "arguments": [
                {
                  "val": "\"Anjali\"",
                  "offset": 17
                }
              ],
              "location": "stepdefinition.DataDrivenTesting.name_of_employee(java.lang.String)"
            },
            "keyword": "Given "
          },
          {
            "result": {
              "duration": 1169000,
              "status": "passed"
            },
            "line": 7,
            "name": "salary of employee \"99000\" in step",
            "match": {
              "arguments": [
                {
                  "val": "\"99000\"",
                  "offset": 19
                }
              ],
              "location": "stepdefinition.DataDrivenTesting.salary_of_employee_in_step(java.lang.String)"
            },
            "keyword": "When "
          },
          {
            "result": {
              "status": "passed"
            },
            "line": 8,
            "name": "company of employee \"Wipro\" in step",
            "match": {
              "arguments": [
                {
                  "val": "\"Wipro\"",
                  "offset": 20
                }
              ],
              "location": "stepdefinition.DataDrivenTesting.company_of_employee_in_step(java.lang.String)"
            },
            "keyword": "Then "
          }
        ],
        "tags": [
          {
            "name": "@ddt"
          }
        ]
      },
      {
        "start_timestamp": "2023-12-16T02:57:23.305Z",
        "before": [
          {
            "result": {
              "duration": 2653043200,
              "status": "passed"
            },
            "match": {
              "location": "hooks.FrameworkHook.setUpConfigFile(io.cucumber.java.Scenario)"
            }
          }
        ],
        "line": 14,
        "name": "Data Driven Testing in scenario outline",
        "description": "",
        "id": "data-driven-testing;data-driven-testing-in-scenario-outline;;4",
        "after": [
          {
            "result": {
              "duration": 145493300,
              "status": "passed"
            },
            "match": {
              "location": "hooks.FrameworkHook.dismantleDriver(io.cucumber.java.Scenario)"
            }
          }
        ],
        "type": "scenario",
        "keyword": "Scenario Outline",
        "steps": [
          {
            "result": {
              "status": "passed"
            },
            "line": 6,
            "name": "Name of employee \"Tushar\"",
            "match": {
              "arguments": [
                {
                  "val": "\"Tushar\"",
                  "offset": 17
                }
              ],
              "location": "stepdefinition.DataDrivenTesting.name_of_employee(java.lang.String)"
            },
            "keyword": "Given "
          },
          {
            "result": {
              "status": "passed"
            },
            "line": 7,
            "name": "salary of employee \"96000\" in step",
            "match": {
              "arguments": [
                {
                  "val": "\"96000\"",
                  "offset": 19
                }
              ],
              "location": "stepdefinition.DataDrivenTesting.salary_of_employee_in_step(java.lang.String)"
            },
            "keyword": "When "
          },
          {
            "result": {
              "duration": 1064000,
              "status": "passed"
            },
            "line": 8,
            "name": "company of employee \"LTI\" in step",
            "match": {
              "arguments": [
                {
                  "val": "\"LTI\"",
                  "offset": 20
                }
              ],
              "location": "stepdefinition.DataDrivenTesting.company_of_employee_in_step(java.lang.String)"
            },
            "keyword": "Then "
          }
        ],
        "tags": [
          {
            "name": "@ddt"
          }
        ]
      }
    ],
    "name": "Data Driven Testing",
    "description": "",
    "id": "data-driven-testing",
    "keyword": "Feature",
    "uri": "file:src/test/resources/Ecommerc%20Product%20Ordering/datadriventesting.feature",
    "tags": []
  }
]